megauploader/__init__.py
megauploader/core.py
megauploader/utils.py
megauploader/utils2.py
megauploader/__metadata__/DISCLIAIMER.md
megauploader/__metadata__/LICENSE
megauploader/__metadata__/README.md
megauploader/__metadata__/__init__.py
megauploader/__metadata__/requirements.txt
megauploader/pkg_data/LICENSE
megauploader/pkg_data/__init__.py
megauploader/pkg_data/crypto.py
megauploader/pkg_data/errors.py
megauploader/pkg_data/mega.py
megauploader-0.6.0.dist-info/METADATA
megauploader-0.6.0.dist-info/WHEEL
megauploader-0.6.0.dist-info/top_level.txt
megauploader-0.6.0.dist-info/RECORD
